transformers_pytorch/__init__.py
transformers_pytorch/transformers.py
transformers_pytorch-1.0.dist-info/licenses/LICENSE
transformers_pytorch-1.0.dist-info/METADATA
transformers_pytorch-1.0.dist-info/WHEEL
transformers_pytorch-1.0.dist-info/top_level.txt
transformers_pytorch-1.0.dist-info/RECORD
