Metadata-Version: 2.4
Name: transformers-pytorch
Version: 1.0
Summary: Transformers in Pytorch
Author-email: Richard Hsieh <rzhsieh@gmail.com>
License: MIT License
Project-URL: Homepage, https://pypi.org/project/transformers-pytorch/
Project-URL: Repository, https://github.com/richsi/transformers-pytorch
Keywords: artificial intelligence,transformers
Classifier: Development Status :: 4 - Beta
Classifier: Programming Language :: Python :: 3
Classifier: Programming Language :: Python :: 3.11
Classifier: License :: OSI Approved :: MIT License
Classifier: Operating System :: OS Independent
Classifier: Intended Audience :: Science/Research
Classifier: Topic :: Scientific/Engineering :: Artificial Intelligence
Requires-Python: >=3.11
License-File: LICENSE
Requires-Dist: torch>=2.0
Provides-Extra: test
Requires-Dist: pytest; extra == "test"
Dynamic: license-file
